LICENSE
README.md
setup.cfg
setup.py
mebots/__init__.py
mebots/main.py
mebots.egg-info/PKG-INFO
mebots.egg-info/SOURCES.txt
mebots.egg-info/dependency_links.txt
mebots.egg-info/requires.txt
mebots.egg-info/top_level.txt