Metadata-Version: 2.1
Name: mebots
Version: 0.3.2
Summary: Library for running GroupMe bots with the MeBots API toolkit.
Home-page: https://github.com/MeBots/mebotspy
Author: Erik Boesen
Author-email: me@erikboesen.com
License: GPL
Platform: UNKNOWN
License-File: LICENSE
